{
    "/js/app.js": "/js/app.js",
    "/css/app.css": "/css/app.css",
    "/js/app.47eac6bc462e364b836b.hot-update.js": "/js/app.47eac6bc462e364b836b.hot-update.js",
    "/js/app.49bd5cb6c0d6699472ef.hot-update.js": "/js/app.49bd5cb6c0d6699472ef.hot-update.js",
    "/js/app.67fe6b5f70f0ceb492a3.hot-update.js": "/js/app.67fe6b5f70f0ceb492a3.hot-update.js",
    "/js/app.27bd5b1dac23aeffca68.hot-update.js": "/js/app.27bd5b1dac23aeffca68.hot-update.js",
    "/js/app.cd8bf0d2b7d959047cdf.hot-update.js": "/js/app.cd8bf0d2b7d959047cdf.hot-update.js",
    "/js/app.b705644809ef131731ec.hot-update.js": "/js/app.b705644809ef131731ec.hot-update.js",
    "/js/app.6190f986aacb76168cb5.hot-update.js": "/js/app.6190f986aacb76168cb5.hot-update.js"
}
